star_pso/__init__.py
star_pso/benchmarks/__init__.py
star_pso/benchmarks/composite_functions.py
star_pso/benchmarks/equal_maxima.py
star_pso/benchmarks/five_uneven_peak_trap.py
star_pso/benchmarks/gaussian_mixture.py
star_pso/benchmarks/himmelblau.py
star_pso/benchmarks/rastrigin.py
star_pso/benchmarks/shubert.py
star_pso/benchmarks/six_hump_camel_back.py
star_pso/benchmarks/test_function.py
star_pso/benchmarks/uneven_decreasing_maxima.py
star_pso/benchmarks/vincent.py
star_pso/engines/__init__.py
star_pso/engines/binary_pso.py
star_pso/engines/categorical_pso.py
star_pso/engines/generic_pso.py
star_pso/engines/integer_pso.py
star_pso/engines/jack_of_all_trades_pso.py
star_pso/engines/quantum_pso.py
star_pso/engines/standard_pso.py
star_pso/population/__init__.py
star_pso/population/jat_particle.py
star_pso/population/particle.py
star_pso/population/swarm.py
star_pso/utils/__init__.py
star_pso/utils/auxiliary.py
star_pso/utils/data_block.py
starpso-0.1.0.dist-info/LICENSE
starpso-0.1.0.dist-info/METADATA
starpso-0.1.0.dist-info/WHEEL
starpso-0.1.0.dist-info/top_level.txt
starpso-0.1.0.dist-info/RECORD
