Metadata-Version: 2.1
Name: starpso
Version: 0.1.0
Summary: Particle Swarm Optimization algorithms toolbox in Python3
Home-page: https://github.com/vrettasm/PyStarPSO
Author: Michalis Vrettas, PhD
Author-email: "Michalis Vrettas, PhD" <michail.vrettas@gmail.com>
License: GPL-3.0
Project-URL: Homepage, https://github.com/vrettasm/PyStarPSO
Keywords: optimization,particle swarm intelligence,algorithms
Classifier: Intended Audience :: Developers
Classifier: Intended Audience :: Education
Classifier: Intended Audience :: Science/Research
Classifier: Programming Language :: Python :: 3
Classifier: Operating System :: OS Independent
Requires-Python: >=3.10
License-File: LICENSE
Requires-Dist: numpy
Requires-Dist: numba
Requires-Dist: scipy
Requires-Dist: joblib
